bhaspylib/__init__.py
bhaspylib/myfunctions.py
bhaspylib-0.1.0.dist-info/METADATA
bhaspylib-0.1.0.dist-info/WHEEL
bhaspylib-0.1.0.dist-info/top_level.txt
bhaspylib-0.1.0.dist-info/RECORD
